[{"Type":"Bandage","ID":0,"Texts":["Je bent nog helemaal heel!"]},{"Type":"Flashlight","ID":0,"Texts":["Je zet de zaklamp uit."]},{"Type":"Flashlight","ID":1,"Texts":["Je zet de zaklamp uit. Je ziet niets meer."]},{"Type":"Flashlight","ID":2,"Texts":["Je zet de zaklamp aan. De straal verlicht de omtrek."]},{"Type":"Flashlight","ID":3,"Texts":["Zonder nieuwe batterijen doet-ie het niet..."]},{"Type":"Flashlight","ID":4,"Texts":["De zaklamp gaat zwakker branden."]},{"Type":"Flashlight","ID":5,"Texts":["De batterijen van de zaklamp zijn uitgeput. Langzaam dooft hij."]},{"Type":"Player","ID":0,"Texts":["Je zakken zitten tsjokvol, en je krijgt {item} er niet in."]},{"Type":"Player","ID":1,"Texts":["Je pakt {item} op en steekt deze in een van je zakken."]},{"Type":"Player","ID":2,"Texts":["Je pakt {item} op en doet hem aan."]},{"Type":"GeneralCommandProcessor","ID":0,"Texts":["Syntax: {command}"]},{"Type":"LocationCommandProcessor","ID":0,"Texts":["Syntax: {command}"]},{"Type":"LocationCommandProcessor","ID":1,"Texts":["Daar kun je niet heen."]},{"Type":"ItemCommandProcessor","ID":0,"Texts":["Syntax: {command} \u003Cvoorwerp\u003E"]},{"Type":"ItemCommandProcessor","ID":1,"Texts":["Je hebt geen \u0022{param}\u0022."]},{"Type":"ItemCommandProcessor","ID":2,"Texts":["De afkorting {param} is dubbelzinnig."]},{"Type":"ItemCommandProcessor.","ID":3,"Texts":["Je ziet hier geen \u0022{param}\u0022 die je kunt meenemen."]}]