[{"Type":"Bandage","ID":0,"Texts":["You\u0027re still in one piece!"]},{"Type":"Flashlight","ID":0,"Texts":["You turn off the flashlight."]},{"Type":"Flashlight","ID":1,"Texts":["You turn off the flashlight. You don\u0027t see a thing anymore."]},{"Type":"Flashlight","ID":2,"Texts":["You turn on the flashlight. The beam lights up your surroundings."]},{"Type":"Flashlight","ID":3,"Texts":["It won\u0027t work without new batteries..."]},{"Type":"Flashlight","ID":4,"Texts":["The light of the flashlight starts to dim."]},{"Type":"Flashlight","ID":5,"Texts":["The batteries in the flaslight are depleted. Slowly, it goes out."]},{"Type":"Sword","ID":0,"Texts":["You strike with your sword, but the monster dodges it."]},{"Type":"Sword","ID":1,"Texts":["You strike with your sword and you hit the monster hard."]},{"Type":"Sword","ID":2,"Texts":["The monster is badly injured and you\u0027re soaked in its blood."]},{"Type":"Sword","ID":3,"Texts":["You can strike again. Do you Want to? [y/n]"]},{"Type":"Sword","ID":4,"Texts":["I didn\u0027t catch that. Please answer with y or n."]},{"Type":"Player","ID":0,"Texts":["Je pockets are filled to the brim and you can\u0027t fit {item} in them."]},{"Type":"Player","ID":1,"Texts":["You pick up {item} and puts it in one of your pockets."]},{"Type":"Player","ID":2,"Texts":["You pick up {item} and puts it on."]},{"Type":"GeneralCommandProcessor","ID":0,"Texts":["Syntax: {command}"]},{"Type":"LocationCommandProcessor","ID":0,"Texts":["Syntax: {command}"]},{"Type":"LocationCommandProcessor","ID":1,"Texts":["You can\u0027t go there."]},{"Type":"ItemCommandProcessor","ID":0,"Texts":["Syntax: {command} \\\u003Cobject\\\u003E"]},{"Type":"ItemCommandProcessor","ID":1,"Texts":["You don\u0027t have a \u0022{param}\u0022"]},{"Type":"ItemCommandProcessor","ID":2,"Texts":["The abbreviation \u0022{param}\u0022 is ambiguous"]},{"Type":"ItemCommandProcessor","ID":3,"Texts":["You don\u0027t see a \u0022{param}\u0022 that you can pick up."]},{"Type":"Engine","ID":0,"Texts":["No command entered"]},{"Type":"Engine","ID":1,"Texts":["Invalid command entered"]},{"Type":"Engine","ID":2,"Texts":["The abbreviation \u0022{command}\u0022 is ambiguous"]},{"Type":"Engine","ID":3,"Texts":["Type h for help."]},{"Type":"Engine","ID":4,"Texts":["You are {room}."]},{"Type":"Engine","ID":5,"Texts":["It\u0027s pitch black and you can\u0027t see your hand in front of your face."]},{"Type":"Engine","ID":6,"Texts":["Around you, you see the smoldering remains of what used to be a forest."]},{"Type":"Engine","ID":7,"Texts":["Here\u0027s {item}.","Here are {items}.","{firstitem} and {seconditem}","{item}, "]},{"Type":"Engine","ID":8,"Texts":["east","west","north","south","up","down","You can go {way}.","You can go {ways}.","{firstway} and {secondway}","{way}, "]},{"Type":"Engine","ID":9,"Texts":["Bathing in your own blood, you succumb to your injuries. While you\u0027re gasping for air on the ground, you hear loud laughter from a distance.","Then your eyes close and your heart stops beating.","At the same time, the bomb explodes and the earth dies with you."]},{"Type":"InternalCommandProcessor","ID":0,"Texts":["Invalid command entered"]}]